realtimelog/__init__.py
realtimelog/log.py
tests/__init__.py
tests/integration/__init__.py
tests/integration/log.py
realtimelog-1.1.2.dist-info/LICENSE
realtimelog-1.1.2.dist-info/METADATA
realtimelog-1.1.2.dist-info/WHEEL
realtimelog-1.1.2.dist-info/top_level.txt
realtimelog-1.1.2.dist-info/RECORD
