Metadata-Version: 2.1
Name: realtimelog
Version: 1.1.2
Summary: Python package for REAL-TIME log, see: https://github.com/cn007b/log, https://realtimelog.herokuapp.com
Home-page: https://github.com/cn007b/pylog
Author: V. Kovpak
Author-email: cn007b@gmail.com
License: UNKNOWN
Platform: UNKNOWN
Classifier: Programming Language :: Python :: 3
Classifier: License :: OSI Approved :: MIT License
Classifier: Operating System :: OS Independent
Requires-Python: >=3.6
